scrapeneatly/__init__.py
scrapeneatly/config.py
scrapeneatly/core.py
scrapeneatly/exceptions.py
scrapeneatly/extractor.py
scrapeneatly/models.py
scrapeneatly/scraper.py
scrapeneatly/test.py
scrapeneatly/utils.py
scrapeneatly-0.1.2.dist-info/LICENSE
scrapeneatly-0.1.2.dist-info/METADATA
scrapeneatly-0.1.2.dist-info/WHEEL
scrapeneatly-0.1.2.dist-info/top_level.txt
scrapeneatly-0.1.2.dist-info/RECORD
