Metadata-Version: 2.2
Name: scrapeneatly
Version: 0.1.2
Summary: A smart web scraper with LLM-powered extraction capabilities
Author-email: Avirath Tibrewala <avirathtibrewala@gmail.com>
Classifier: Development Status :: 3 - Alpha
Classifier: Intended Audience :: Developers
Classifier: License :: OSI Approved :: MIT License
Classifier: Operating System :: OS Independent
Classifier: Programming Language :: Python :: 3
Classifier: Programming Language :: Python :: 3.8
Classifier: Programming Language :: Python :: 3.9
Classifier: Programming Language :: Python :: 3.10
Classifier: Programming Language :: Python :: 3.11
Requires-Python: >=3.8
License-File: LICENSE
Requires-Dist: aiohttp>=3.8.0
Requires-Dist: beautifulsoup4>=4.9.3
Requires-Dist: fake-useragent>=0.1.11
Requires-Dist: playwright>=1.20.0
Requires-Dist: pydantic>=2.0.0
Requires-Dist: tiktoken>=0.3.0
Requires-Dist: openai>=1.0.0
Requires-Dist: lxml>=4.9.0
